automl/__init__.py
automl/cli.py
automl/dimensionality_reduction.py
automl/encoder.py
automl/evaluator.py
automl/feature_importance.py
automl/feature_selection.py
automl/main.py
automl/model_selection.py
automl/outliers.py
automl/preprocessor.py
automl/scaler.py
automl/test_transformer.py
automl/utils.py
automlite/__init__.py
automlite/cli.py
automlite/dimensionality_reduction.py
automlite/encoder.py
automlite/evaluator.py
automlite/feature_importance.py
automlite/feature_selection.py
automlite/main.py
automlite/model_selection.py
automlite/outliers.py
automlite/preprocessor.py
automlite/scaler.py
automlite/test_transformer.py
automlite/utils.py
tests/__init__.py
tests/test_dimensionality_reduction.py
tests/test_encoder.py
tests/test_evaluator.py
tests/test_feature_importance.py
tests/test_feature_selection.py
tests/test_model_selection.py
tests/test_outliers.py
tests/test_preprocessor.py
tests/test_scaler.py
tests/test_split.py
tests/test_test_transformer.py
tests/test_utils.py
automlite-0.1.7.dist-info/METADATA
automlite-0.1.7.dist-info/WHEEL
automlite-0.1.7.dist-info/entry_points.txt
automlite-0.1.7.dist-info/top_level.txt
automlite-0.1.7.dist-info/RECORD
